json_graph_traversal/__init__.py
json_graph_traversal/traversal.py
json_graph_traversal-0.1.0.dist-info/METADATA
json_graph_traversal-0.1.0.dist-info/WHEEL
json_graph_traversal-0.1.0.dist-info/top_level.txt
json_graph_traversal-0.1.0.dist-info/RECORD
